duomai/__init__.py
duomai/duomai.py
duomai/utils.py
duomai-10.0.0.dist-info/LICENSE
duomai-10.0.0.dist-info/METADATA
duomai-10.0.0.dist-info/WHEEL
duomai-10.0.0.dist-info/top_level.txt
duomai-10.0.0.dist-info/RECORD
