Metadata-Version: 2.1
Name: duomai
Version: 10.0.0
Summary: Duomai Open Service SDK
Home-page: https://open.duomai.com/
Author: Sans
Author-email: Sans@duomai.com
License: UNKNOWN
Platform: UNKNOWN
Classifier: Programming Language :: Python :: 3
Classifier: License :: OSI Approved :: MIT License
Classifier: Operating System :: OS Independent
Requires-Python: >=3.6
Requires-Dist: requests>=2.28.2
Requires-Dist: urllib3>=1.26.3
